Workbook

Sheet Requerimientos
B2: Arken — Requerimientos funcionales
B4: Actores:
B6: AG: Admin General - Dueño de la automotora. Ve y gestiona todas sus sucursales.
B7: AS: Admin de Sucursal - Mismos permisos que el Admin General, acotado a su sucursal.
B8: VE: Vendedor - Acotado a su sucursal. No ve costos, márgenes ni gastos; no anula ni administra.
B9: VI: Visitante - Comprador o público general, anónimo, en el sitio público.
B10: CL: Cliente - Cliente de la automotora que recibe correos (no usa el sistema).
B11: SIS: Sistema - Procesos automáticos (tareas programadas, validaciones, cálculos).
B13: ID | C13: Módulo | D13: Submódulo | E13: Requerimiento | F13: Actor
B14: RF-01.01 | C14: 1. Registro de automotoras | D14: — | E14: El sistema debe ofrecer un formulario público para registrar una automotora nueva. | F14: VI
B15: RF-01.02 | C15: 1. Registro de automotoras | D15: — | E15: El formulario debe solicitar los datos de la empresa: nombre, RUT, dirección, teléfono y correo. | F15: VI
B16: RF-01.03 | C16: 1. Registro de automotoras | D16: — | E16: El formulario debe solicitar los datos del usuario inicial: nombre, correo y contraseña. | F16: VI
B17: RF-01.04 | C17: 1. Registro de automotoras | D17: — | E17: El sistema debe permitir elegir el subdominio de la vitrina y validar en línea que esté disponible, que tenga un formato válido (sin espacios ni caracteres especiales) y que no sea una palabra reservada. | F17: VI, SIS
B18: RF-01.05 | C18: 1. Registro de automotoras | D18: — | E18: El sistema debe validar el RUT de la empresa (dígito verificador) y darle formato automático mientras se escribe. | F18: SIS
B19: RF-01.06 | C19: 1. Registro de automotoras | D19: — | E19: El registro debe crear, en una sola operación, la automotora, su sucursal principal (con la dirección y el teléfono ingresados) y el usuario inicial con rol Admin General. | F19: SIS
B20: RF-01.07 | C20: 1. Registro de automotoras | D20: — | E20: La automotora debe quedar activa de inmediato, sin aprobación manual de la plataforma, con su inventario vacío. | F20: SIS
B21: RF-01.08 | C21: 1. Registro de automotoras | D21: — | E21: El sistema debe enviar un correo de verificación al usuario inicial y bloquear su inicio de sesión hasta que verifique su correo. | F21: SIS
B22: RF-01.09 | C22: 1. Registro de automotoras | D22: — | E22: El subdominio no debe poder modificarse después del registro. | F22: SIS
B23: RF-02.01 | C23: 2. Marketplace global | D23: — | E23: El sitio público debe ser accesible sin registro ni inicio de sesión. | F23: VI
B24: RF-02.02 | C24: 2. Marketplace global | D24: — | E24: La portada debe mostrar un buscador rápido por texto, marca, tipo de vehículo, región y precio máximo. | F24: VI
... B289: RF-19.12 | C289: 19. Requerimientos transversales del panel de gestión | D289: — | E289: El título de la pestaña del navegador debe reflejar la pantalla actual. | F289: SIS

Sheet Resumen
A1: Resumen por módulo
A3: Módulo | B3: Cantidad | C3: % del total | E3: Actor | F3: Requerimientos donde participa
A4: 1. Registro de automotoras | B4: =COUNTIF(Requerimientos!$C$14:$C$289,A4) -> 9 | C4: =IFERROR(B4/$B$23,0) -> 0.032608696 | E4: AG | F4: =COUNTIF(Requerimientos!$F$14:$F$289,"*"&E4&"*") -> 53 | G4: Admin General
A5: 2. Marketplace global | B5: =COUNTIF(Requerimientos!$C$14:$C$289,A5) -> 24 | C5: =IFERROR(B5/$B$23,0) -> 0.086956522 | E5: AS | F5: =COUNTIF(Requerimientos!$F$14:$F$289,"*"&E5&"*") -> 37 | G5: Admin de Sucursal
A6: 3. Vitrina (perfil público) de la automotora | B6: =COUNTIF(Requerimientos!$C$14:$C$289,A6) -> 18 | C6: =IFERROR(B6/$B$23,0) -> 0.065217391 | E6: VE | F6: =COUNTIF(Requerimientos!$F$14:$F$289,"*"&E6&"*") -> 3 | G6: Vendedor
A7: 4. Sucursales | B7: =COUNTIF(Requerimientos!$C$14:$C$289,A7) -> 9 | C7: =IFERROR(B7/$B$23,0) -> 0.032608696 | E7: Todos | F7: =COUNTIF(Requerimientos!$F$14:$F$289,"*"&E7&"*") -> 80 | G7: Todos (AG, AS y VE)
A8: 5. Usuarios, roles y autenticación | B8: =COUNTIF(Requerimientos!$C$14:$C$289,A8) -> 24 | C8: =IFERROR(B8/$B$23,0) -> 0.086956522 | E8: VI | F8: =COUNTIF(Requerimientos!$F$14:$F$289,"*"&E8&"*") -> 29 | G8: Visitante
A9: 6. Clientes (CRM) | B9: =COUNTIF(Requerimientos!$C$14:$C$289,A9) -> 10 | C9: =IFERROR(B9/$B$23,0) -> 0.036231884 | E9: CL | F9: =COUNTIF(Requerimientos!$F$14:$F$289,"*"&E9&"*") -> 4 | G9: Cliente
A10: 7. Vehículos e inventario | B10: =COUNTIF(Requerimientos!$C$14:$C$289,A10) -> 36 | C10: =IFERROR(B10/$B$23,0) -> 0.13043478 | E10: SIS | F10: =COUNTIF(Requerimientos!$F$14:$F$289,"*"&E10&"*") -> 113 | G10: Sistema
A11: 8. Gastos | B11: =COUNTIF(Requerimientos!$C$14:$C$289,A11) -> 15 | C11: =IFERROR(B11/$B$23,0) -> 0.054347826
A12: 9. Consignaciones | B12: =COUNTIF(Requerimientos!$C$14:$C$289,A12) -> 13 | C12: =IFERROR(B12/$B$23,0) -> 0.047101449 | E12: Nota: un requerimiento puede tener más de un actor, por lo que esta columna no suma el total.
A13: 10. Documentos comerciales | B13: =COUNTIF(Requerimientos!$C$14:$C$289,A13) -> 27 | C13: =IFERROR(B13/$B$23,0) -> 0.097826087
A14: 11. Ventas | B14: =COUNTIF(Requerimientos!$C$14:$C$289,A14) -> 12 | C14: =IFERROR(B14/$B$23,0) -> 0.043478261
A15: 12. Anulación y cancelación | B15: =COUNTIF(Requerimientos!$C$14:$C$289,A15) -> 7 | C15: =IFERROR(B15/$B$23,0) -> 0.025362319
A16: 13. Notificaciones internas | B16: =COUNTIF(Requerimientos!$C$14:$C$289,A16) -> 8 | C16: =IFERROR(B16/$B$23,0) -> 0.028985507
A17: 14. Dashboard del negocio | B17: =COUNTIF(Requerimientos!$C$14:$C$289,A17) -> 12 | C17: =IFERROR(B17/$B$23,0) -> 0.043478261
A18: 15. Analítica | B18: =COUNTIF(Requerimientos!$C$14:$C$289,A18) -> 13 | C18: =IFERROR(B18/$B$23,0) -> 0.047101449
A19: 16. Auditoría | B19: =COUNTIF(Requerimientos!$C$14:$C$289,A19) -> 7 | C19: =IFERROR(B19/$B$23,0) -> 0.025362319
A20: 17. Configuración de la automotora | B20: =COUNTIF(Requerimientos!$C$14:$C$289,A20) -> 8 | C20: =IFERROR(B20/$B$23,0) -> 0.028985507
A21: 18. Correos al cliente | B21: =COUNTIF(Requerimientos!$C$14:$C$289,A21) -> 12 | C21: =IFERROR(B21/$B$23,0) -> 0.043478261
A22: 19. Requerimientos transversales del panel de gestión | B22: =COUNTIF(Requerimientos!$C$14:$C$289,A22) -> 12 | C22: =IFERROR(B22/$B$23,0) -> 0.043478261
A23: Total | B23: =SUM(B4:B22) -> 276 | C23: =IFERROR(B23/B23,0) -> 1

Sheet Actores
A1: Sigla | B1: Actor | C1: Descripción
A2: AG | B2: Admin General | C2: Dueño de la automotora. Ve y gestiona todas sus sucursales.
A3: AS | B3: Admin de Sucursal | C3: Mismos permisos que el Admin General, acotado a su sucursal.
A4: VE | B4: Vendedor | C4: Acotado a su sucursal. No ve costos, márgenes ni gastos; no anula ni administra.
A5: VI | B5: Visitante | C5: Comprador o público general, anónimo, en el sitio público.
A6: CL | B6: Cliente | C6: Cliente de la automotora que recibe correos (no usa el sistema).
A7: SIS | B7: Sistema | C7: Procesos automáticos (tareas programadas, validaciones, cálculos).
A9: «Todos» equivale a AG, AS y VE (usuarios autenticados del panel).
